ome_zarr_models/__init__.py
ome_zarr_models/_cli.py
ome_zarr_models/_utils.py
ome_zarr_models/base.py
ome_zarr_models/exceptions.py
ome_zarr_models/py.typed
ome_zarr_models/_v06/__init__.py
ome_zarr_models/_v06/axes.py
ome_zarr_models/_v06/base.py
ome_zarr_models/_v06/coordinate_transformations.py
ome_zarr_models/_v06/hcs.py
ome_zarr_models/_v06/image.py
ome_zarr_models/_v06/image_label.py
ome_zarr_models/_v06/image_label_types.py
ome_zarr_models/_v06/labels.py
ome_zarr_models/_v06/multiscales.py
ome_zarr_models/_v06/plate.py
ome_zarr_models/_v06/well.py
ome_zarr_models/_v06/well_types.py
ome_zarr_models/common/__init__.py
ome_zarr_models/common/coordinate_transformations.py
ome_zarr_models/common/image_label_types.py
ome_zarr_models/common/omero.py
ome_zarr_models/common/plate.py
ome_zarr_models/common/validation.py
ome_zarr_models/common/well.py
ome_zarr_models/common/well_types.py
ome_zarr_models/v04/__init__.py
ome_zarr_models/v04/axes.py
ome_zarr_models/v04/base.py
ome_zarr_models/v04/bioformats2raw.py
ome_zarr_models/v04/coordinate_transformations.py
ome_zarr_models/v04/hcs.py
ome_zarr_models/v04/image.py
ome_zarr_models/v04/image_label.py
ome_zarr_models/v04/image_label_types.py
ome_zarr_models/v04/labels.py
ome_zarr_models/v04/multiscales.py
ome_zarr_models/v04/omero.py
ome_zarr_models/v04/plate.py
ome_zarr_models/v04/well.py
ome_zarr_models/v04/well_types.py
ome_zarr_models/v05/__init__.py
ome_zarr_models/v05/axes.py
ome_zarr_models/v05/base.py
ome_zarr_models/v05/bioformats2raw.py
ome_zarr_models/v05/coordinate_transformations.py
ome_zarr_models/v05/hcs.py
ome_zarr_models/v05/image.py
ome_zarr_models/v05/image_label.py
ome_zarr_models/v05/image_label_types.py
ome_zarr_models/v05/labels.py
ome_zarr_models/v05/multiscales.py
ome_zarr_models/v05/plate.py
ome_zarr_models/v05/well.py
ome_zarr_models/v05/well_types.py
ome_zarr_models-1.5.dist-info/METADATA
ome_zarr_models-1.5.dist-info/WHEEL
ome_zarr_models-1.5.dist-info/entry_points.txt
ome_zarr_models-1.5.dist-info/licenses/LICENSE
ome_zarr_models-1.5.dist-info/RECORD
