Metadata-Version: 2.4
Name: ome-zarr-models
Version: 1.5
Summary: A minimal Python package for reading OME-Zarr (meta)data 
Project-URL: Documentation, https://ome-zarr-models-py.readthedocs.io
Project-URL: Repository, https://github.com/ome-zarr-models/ome-zarr-models-py
Project-URL: Bug Tracker, https://github.com/ome-zarr-models/ome-zarr-models-py/issues
Maintainer: David Stansby
License: Copyright 2024 ome-zarr-models-py developers.
License-File: LICENSE
Classifier: Development Status :: 4 - Beta
Classifier: License :: OSI Approved :: MIT License
Classifier: Natural Language :: English
Classifier: Programming Language :: Python
Requires-Python: >=3.11
Requires-Dist: pydantic-zarr>=0.8.2
Requires-Dist: pydantic>=2.11.5
Requires-Dist: zarr>=3.1.1
Provides-Extra: docs
Requires-Dist: fsspec[http]==2025.9.0; extra == 'docs'
Requires-Dist: griffe-pydantic==1.1.7; extra == 'docs'
Requires-Dist: matplotlib==3.10.6; extra == 'docs'
Requires-Dist: mkdocs-jupyter==0.25.1; extra == 'docs'
Requires-Dist: mkdocs-material==9.6.21; extra == 'docs'
Requires-Dist: mkdocs==1.6.1; extra == 'docs'
Requires-Dist: mkdocstrings-python==1.18.2; extra == 'docs'
Requires-Dist: rich==14.1.0; extra == 'docs'
